PyLogger/__init__.py
PyLogger/core.py
pyloggercg-0.1.0.dist-info/METADATA
pyloggercg-0.1.0.dist-info/WHEEL
pyloggercg-0.1.0.dist-info/top_level.txt
pyloggercg-0.1.0.dist-info/RECORD
