Metadata-Version: 2.1
Name: pyloggercg
Version: 0.1.0
Author: CoolGuy158-Git
License: MIT
Keywords: Terminal Logger Simple Syntax For Python
Classifier: Programming Language :: Python :: 3
Classifier: License :: OSI Approved :: MIT License
Classifier: Operating System :: OS Independent
Requires-Python: >=3.7
